osmx/__init__.py
osmx/messages.capnp
osmx/osmx.py
osmx-0.0.5.dist-info/METADATA
osmx-0.0.5.dist-info/WHEEL
osmx-0.0.5.dist-info/top_level.txt
osmx-0.0.5.dist-info/RECORD
