Metadata-Version: 2.1
Name: osmx
Version: 0.0.5
Summary: Read OSM Express (.osmx) database files.
Home-page: https://github.com/protomaps/OSMExpress
Author: Brandon Liu
Author-email: brandon@protomaps.com
License: BSD-2-Clause
Platform: UNKNOWN
Classifier: Programming Language :: Python :: 3
Classifier: License :: OSI Approved :: BSD License
Classifier: Operating System :: OS Independent
